README.md
setup.py
graphcall/__init__.py
graphcall.egg-info/PKG-INFO
graphcall.egg-info/SOURCES.txt
graphcall.egg-info/dependency_links.txt
graphcall.egg-info/requires.txt
graphcall.egg-info/top_level.txt
graphcall/interfaces/__init__.py
graphcall/interfaces/compilable.py
graphcall/nodes/__init__.py
graphcall/nodes/edge.py
graphcall/nodes/node.py
graphcall/nodes/parameter_field.py
graphcall/requests/__init__.py
graphcall/requests/request.py