Metadata-Version: 2.1
Name: graphcall
Version: 0.0.15
Summary: A lightweight graphQL library
Home-page: https://github.com/nwmqpa/GraphCall
Author: nwmqpa
Author-email: thomas.nicollet@epitech.eu
License: UNKNOWN
Platform: UNKNOWN
Classifier: Programming Language :: Python :: 3
Classifier: Operating System :: OS Independent
